README.md
setup.cfg
setup.py
deepak_test_mypackage.egg-info/PKG-INFO
deepak_test_mypackage.egg-info/SOURCES.txt
deepak_test_mypackage.egg-info/dependency_links.txt
deepak_test_mypackage.egg-info/not-zip-safe
deepak_test_mypackage.egg-info/top_level.txt
mypackage/__init__.py
mypackage/exceptions.py